{
    "key": "group_5a3a8a1d9b266",
    "title": "Events",
    "fields": [
        {
            "key": "field_5afdd26f094e8",
            "label": "Related Resources",
            "name": "events_resources",
            "type": "relationship",
            "instructions": "",
            "required": 0,
            "conditional_logic": 0,
            "wrapper": {
                "width": "",
                "class": "",
                "id": ""
            },
            "post_type": [
                "ncecf-resource"
            ],
            "taxonomy": [],
            "filters": [
                "search",
                "taxonomy"
            ],
            "elements": "",
            "min": "",
            "max": "",
            "return_format": "object"
        }
    ],
    "location": [
        [
            {
                "param": "post_type",
                "operator": "==",
                "value": "tribe_events"
            }
        ]
    ],
    "menu_order": 0,
    "position": "normal",
    "style": "seamless",
    "label_placement": "top",
    "instruction_placement": "label",
    "hide_on_screen": "",
    "active": 1,
    "description": "",
    "modified": 1526584087
}